hydra_plugins/hydra_submitit_extension/__init__.py
hydra_plugins/hydra_submitit_extension/config.py
hydra_plugins/hydra_submitit_extension/submitit_launcher.py
hydra_plugins/hydra_submitit_extension/utils/slurm_info.py
hydra_submitit_extension-0.0.5.dist-info/LICENSE.txt
hydra_submitit_extension-0.0.5.dist-info/METADATA
hydra_submitit_extension-0.0.5.dist-info/WHEEL
hydra_submitit_extension-0.0.5.dist-info/top_level.txt
hydra_submitit_extension-0.0.5.dist-info/RECORD
