Metadata-Version: 2.1
Name: hydra-submitit-extension
Version: 0.0.5
Summary: A more flexible hydra submitit launcher
Home-page: https://github.com/caplett/hydra_submitit_extension
Author: Stefan Geyer
Author-email: git@caplett.com
License: MIT
Platform: any
Classifier: Development Status :: 3 - Alpha
Classifier: Programming Language :: Python
License-File: LICENSE.txt
Requires-Dist: hydra-core (<2.0,>=1.1.2)
Requires-Dist: hydra-submitit-launcher (<2.0,>=1.2.0)
Requires-Dist: submitit (<2.0,>=1.4.5)
Provides-Extra: testing
Requires-Dist: setuptools ; extra == 'testing'
Requires-Dist: pytest ; extra == 'testing'
Requires-Dist: pytest-cov ; extra == 'testing'
